.flow
.hgignore
.hgtags
CHANGES.txt
LICENSE.txt
MANIFEST.in
README.txt
bootstrap.py
buildout.cfg
setup.py
bin/minify
bin/update
js/__init__.py
js.jquery_timepicker_addon.egg-info/PKG-INFO
js.jquery_timepicker_addon.egg-info/SOURCES.txt
js.jquery_timepicker_addon.egg-info/dependency_links.txt
js.jquery_timepicker_addon.egg-info/entry_points.txt
js.jquery_timepicker_addon.egg-info/namespace_packages.txt
js.jquery_timepicker_addon.egg-info/not-zip-safe
js.jquery_timepicker_addon.egg-info/requires.txt
js.jquery_timepicker_addon.egg-info/top_level.txt
js/jquery_timepicker_addon/__init__.py
js/jquery_timepicker_addon/test_jquery-timepicker-addon.txt
js/jquery_timepicker_addon/resources/index.html
js/jquery_timepicker_addon/resources/jquery-ui-sliderAccess.js
js/jquery_timepicker_addon/resources/jquery-ui-sliderAccess.min.js
js/jquery_timepicker_addon/resources/jquery-ui-timepicker-addon.css
js/jquery_timepicker_addon/resources/jquery-ui-timepicker-addon.js
js/jquery_timepicker_addon/resources/jquery-ui-timepicker-addon.min.css
js/jquery_timepicker_addon/resources/jquery-ui-timepicker-addon.min.js
js/jquery_timepicker_addon/resources/localization/jquery-ui-timepicker-addon-i18n.js
js/jquery_timepicker_addon/resources/localization/jquery-ui-timepicker-addon-i18n.min.js
js/jquery_timepicker_addon/resources/localization/jquery-ui-timepicker-af.js
js/jquery_timepicker_addon/resources/localization/jquery-ui-timepicker-af.min.js
js/jquery_timepicker_addon/resources/localization/jquery-ui-timepicker-am.js
js/jquery_timepicker_addon/resources/localization/jquery-ui-timepicker-am.min.js
js/jquery_timepicker_addon/resources/localization/jquery-ui-timepicker-bg.js
js/jquery_timepicker_addon/resources/localization/jquery-ui-timepicker-bg.min.js
js/jquery_timepicker_addon/resources/localization/jquery-ui-timepicker-ca.js
js/jquery_timepicker_addon/resources/localization/jquery-ui-timepicker-ca.min.js
js/jquery_timepicker_addon/resources/localization/jquery-ui-timepicker-cs.js
js/jquery_timepicker_addon/resources/localization/jquery-ui-timepicker-cs.min.js
js/jquery_timepicker_addon/resources/localization/jquery-ui-timepicker-da.js
js/jquery_timepicker_addon/resources/localization/jquery-ui-timepicker-da.min.js
js/jquery_timepicker_addon/resources/localization/jquery-ui-timepicker-de.js
js/jquery_timepicker_addon/resources/localization/jquery-ui-timepicker-de.min.js
