Metadata-Version: 1.0
Name: js.jquery-timepicker-addon
Version: 1.5.3
Summary: Fanstatic packaging of jQuery-Timepicker-Addon
Home-page: UNKNOWN
Author: Fanstatic Developers
Author-email: fanstatic@googlegroups.com
License: BSD
Platform: UNKNOWN
